getenv.py
getenv-0.1.0.dist-info/DESCRIPTION.rst
getenv-0.1.0.dist-info/METADATA
getenv-0.1.0.dist-info/RECORD
getenv-0.1.0.dist-info/WHEEL
getenv-0.1.0.dist-info/metadata.json
getenv-0.1.0.dist-info/top_level.txt
