Metadata-Version: 2.0
Name: getenv
Version: 0.1.0
Summary: Environment variable definition with type
Home-page: https://github.com/reorx/getenv
Author: reorx
Author-email: novoreorx@gmail.com
License: License :: OSI Approved :: MIT License
Platform: UNKNOWN
